
    <problem display_name="Multiple Choice">
        <multiplechoiceresponse>
            <label>Which of the following is a type of reinforcement learning approach?</label>
            <description>You can add an optional tip or note related to the prompt like this.</description>
            <choicegroup>
                <choice correct="true">Q learning</choice>
                <choice correct="false">End-to-end approach</choice>
                <choice correct="false">Bootstrapping</choice>
                <choice correct="false">None of the above</choice>
            </choicegroup>
        </multiplechoiceresponse>
    </problem>
    